MANIFEST.in
README.md
setup.py
KeynoteC.egg-info/PKG-INFO
KeynoteC.egg-info/SOURCES.txt
KeynoteC.egg-info/dependency_links.txt
KeynoteC.egg-info/entry_points.txt
KeynoteC.egg-info/top_level.txt
keynotec/__init__.py
keynotec/__main__.py
keynotec/parser.py
keynotec/resources/metadata.inc
keynotec/resources/presentation.tex
keynotec/resources/images/Tuxgaucho.png
keynotec/resources/images/chalkboard.jpg
keynotec/resources/images/fecomercio_senac.png
keynotec/resources/images/film_sprocket.png
keynotec/resources/images/film_strip.png
keynotec/resources/images/invaders.jpg
keynotec/resources/images/senac.png
keynotec/resources/listings/python.tex
keynotec/resources/listings/swift.tex
keynotec/resources/themes/apple_keynote_black.tex
keynotec/resources/themes/chalkboard.tex
keynotec/resources/themes/fspoa.tex
keynotec/resources/themes/invaders.tex
keynotec/resources/themes/photographie.tex
keynotec/resources/themes/photoroll.tex
keynotec/resources/themes/tchelinux.tex