Metadata-Version: 2.1
Name: KeynoteC
Version: 0.2.2
Summary: KeynoteC is a DSL processor for creting keynotes with Latex.
Home-page: https://github.com/rafasgj/keynotec
Author: Rafael Guterres Jeffman
Author-email: rafasgj@gmail.com
License: GPLv3
Keywords: DSL keynote Latex Beamer slides
Platform: any
